pychemiq/Molecules.py
pychemiq/Operators.py
pychemiq/Optimizer.py
pychemiq/RealChip.py
pychemiq/Utils.py
pychemiq/__init__.py
pychemiq/getUniqueId.jar
pychemiq/libcurl.dll
pychemiq/msvcr120.dll
pychemiq/pychemiq.cp310-win_amd64.pyd
pychemiq/test_pychemiq.py
pychemiq/test_pychemiq1_1.py
pychemiq/tox.ini
pychemiq/Circuit/Ansatz.py
pychemiq/Circuit/__pycache__/Ansatz.cpython-39.pyc
pychemiq/Transform/Mapping.py
pychemiq/__pycache__/Molecules.cpython-39.pyc
pychemiq/__pycache__/Optimizer.cpython-39.pyc
pychemiq/__pycache__/__init__.cpython-310.pyc
pychemiq/basis/2zapanr.g94
pychemiq/basis/2zapanrcv.g94
pychemiq/basis/321g.g94
pychemiq/basis/3zapanr.g94
pychemiq/basis/3zapanrcv.g94
pychemiq/basis/431g.g94
pychemiq/basis/4zapanr.g94
pychemiq/basis/4zapanrcv.g94
pychemiq/basis/521g.g94
pychemiq/basis/621g.g94
pychemiq/basis/631++g.g94
pychemiq/basis/631++g_.g94
pychemiq/basis/631++g__.g94
pychemiq/basis/631++g__j.g94
pychemiq/basis/631+g.g94
pychemiq/basis/631+g_.g94
pychemiq/basis/631+g__.g94
pychemiq/basis/631+g_j.g94
"pychemiq/basis/6311++g(2d,2p).g94"
"pychemiq/basis/6311++g(3df,3pd).g94"
pychemiq/basis/6311++g.g94
pychemiq/basis/6311++g_.g94
pychemiq/basis/6311++g__.g94
pychemiq/basis/6311++g__j.g94
"pychemiq/basis/6311+g(2d,p).g94"
pychemiq/basis/6311+g.g94
pychemiq/basis/6311+g_.g94
pychemiq/basis/6311+g__.g94
pychemiq/basis/6311+g_j.g94
"pychemiq/basis/6311g(2df,2pd).g94"
"pychemiq/basis/6311g(d,p).g94"
pychemiq/basis/6311g.g94
pychemiq/basis/6311g_.g94
pychemiq/basis/6311g__.g94
pychemiq/basis/6311g__rifit.g94
pychemiq/basis/6311gj.g94
"pychemiq/basis/6311xxg(d,p).g94"
"pychemiq/basis/631g(2df,p).g94"
"pychemiq/basis/631g(3df,3pd).g94"
"pychemiq/basis/631g(d,p).g94"
pychemiq/basis/631g.g94
pychemiq/basis/631g_.g94
pychemiq/basis/631g__.g94
pychemiq/basis/631g__rifit.g94
pychemiq/basis/631g_blaudeau.g94
pychemiq/basis/631gblaudeau.g94
pychemiq/basis/631gj.g94
pychemiq/basis/acv2zj.g94
pychemiq/basis/acv3zj.g94
pychemiq/basis/acv4zj.g94
pychemiq/basis/admm1.g94
pychemiq-1.1.4.dist-info/METADATA
pychemiq-1.1.4.dist-info/WHEEL
pychemiq-1.1.4.dist-info/top_level.txt
pychemiq-1.1.4.dist-info/RECORD
