Metadata-Version: 2.1
Name: pychemiq
Version: 1.1.4
Author: OriginQ
License: Apache Licence
Requires-Dist: numpy >=1.20.0
